simpegEM1D/DigFilter.py
simpegEM1D/EM1D.py
simpegEM1D/EM1DAnalytics.py
simpegEM1D/EM1DSimulation.py
simpegEM1D/GlobalEM1D.py
simpegEM1D/IO.py
simpegEM1D/Kernels.py
simpegEM1D/KnownSystems.py
simpegEM1D/RTEfun.py
simpegEM1D/RTEfun_vec.py
simpegEM1D/Regularization.py
simpegEM1D/Survey.py
simpegEM1D/Utils1D.py
simpegEM1D/Waveform.py
simpegEM1D/Waveforms.py
simpegEM1D/__init__.py
simpegEM1D/dummy.py
simpegEM1D/m_rTE_Fortran.cpython-36m-darwin.so
simpegEM1D-0.0.16.dist-info/METADATA
simpegEM1D-0.0.16.dist-info/RECORD
simpegEM1D-0.0.16.dist-info/WHEEL
simpegEM1D-0.0.16.dist-info/top_level.txt
tests/__init__.py
tests/testEM1D_FD_fwd.py
tests/testEM1D_FD_jac_layers.py
tests/testEM1D_TD_dual_moment_fwd.py
tests/testEM1D_TD_general_fwd.py
tests/testEM1D_TD_general_jac_layers.py
tests/testEM1D_TD_off_fwd.py
tests/testEM1D_TD_off_jac_layers.py
tests/testGlobalEM1D_FD_jac_layers.py
tests/testGlobalEM1D_TD_jac_layers.py
