Metadata-Version: 2.1
Name: simpegEM1D
Version: 0.0.16
Summary: simpegEM1D
Home-page: https://github.com/simpeg/simpegEM1D
Author: Seogi Kang
Author-email: skang@eoas.ubc.ca
License: MIT License
Download-URL: https://github.com/simpeg/simpegEM1D
Keywords: geophysics,electromagnetics
Platform: Windows
Platform: Linux
Platform: Solaris
Platform: Mac OS-X
Platform: Unix
Classifier: Development Status :: 4 - Beta
Classifier: Intended Audience :: Education
Classifier: Intended Audience :: Science/Research
Classifier: License :: OSI Approved :: MIT License
Classifier: Programming Language :: Python
Classifier: Topic :: Scientific/Engineering
Classifier: Topic :: Scientific/Engineering :: Mathematics
Classifier: Topic :: Scientific/Engineering :: Physics
Classifier: Operating System :: Microsoft :: Windows
Classifier: Operating System :: POSIX
Classifier: Operating System :: Unix
Classifier: Operating System :: MacOS
Classifier: Natural Language :: English
Requires-Dist: SimPEG (>=0.4.1)
Requires-Dist: empymod (>=1.6.2)
Requires-Dist: multiprocess
